LICENSE
MANIFEST.in
README.rst
setup.py
twunnel/__init__.py
twunnel/dns_resolver.py
twunnel/generator.py
twunnel/generator__ssh.py
twunnel/generator__ssl.py
twunnel/local_proxy_server.py
twunnel/local_proxy_server__https.py
twunnel/local_proxy_server__socks4.py
twunnel/local_proxy_server__socks5.py
twunnel/local_proxy_server__ssh.py
twunnel/local_proxy_server__ssl.py
twunnel/local_proxy_server__ws.py
twunnel/logger.py
twunnel/proxy_server.py
twunnel/proxy_server__https.py
twunnel/proxy_server__socks4.py
twunnel/proxy_server__socks5.py
twunnel/remote_proxy_server.py
twunnel/remote_proxy_server__ssh.py
twunnel/remote_proxy_server__ssl.py
twunnel/remote_proxy_server__ws.py
twunnel.egg-info/PKG-INFO
twunnel.egg-info/SOURCES.txt
twunnel.egg-info/dependency_links.txt
twunnel.egg-info/requires.txt
twunnel.egg-info/top_level.txt