Metadata-Version: 1.1
Name: twunnel
Version: 0.14.0
Summary: A HTTPS/SOCKS4/SOCKS5 tunnel for Twisted.
Home-page: https://github.com/jvansteirteghem/twunnel
Author: Jeroen Van Steirteghem
Author-email: jeroen.vansteirteghem@gmail.com
License: MIT
Platform: UNKNOWN
Classifier: Development Status :: 4 - Beta
Classifier: Environment :: Web Environment
Classifier: Framework :: Twisted
Classifier: Intended Audience :: Developers
Classifier: License :: OSI Approved :: MIT License
Classifier: Operating System :: OS Independent
Classifier: Programming Language :: Python
Classifier: Programming Language :: Python :: 2
Classifier: Programming Language :: Python :: 2.7
Classifier: Programming Language :: Python :: Implementation :: CPython
Classifier: Programming Language :: Python :: Implementation :: PyPy
Classifier: Topic :: Internet
Classifier: Topic :: Software Development :: Libraries :: Python Modules
